wev/VERSION
wev/__init__.py
wev/__main__.py
wev/cli.py
wev/conftest.py
wev/exceptions.py
wev/executor.py
wev/explainer.py
wev/mock_plugin.py
wev/plugins.py
wev/resolution_cache.py
wev/resolver.py
wev/test_cli.py
wev/test_exceptions.py
wev/test_executor.py
wev/test_explainer.py
wev/test_plugins.py
wev/test_resolution_cache.py
wev/test_resolver.py
wev/test_variable.py
wev/test_version.py
wev/variable.py
wev/version.py
wev/logging/__init__.py
wev/logging/formatter.py
wev/logging/log.py
wev/logging/py.typed
wev/logging/test_log.py
wev/sdk/__init__.py
wev/sdk/exceptions.py
wev/sdk/plugin_base.py
wev/sdk/plugin_configuration.py
wev/sdk/py.typed
wev/sdk/resolution.py
wev/sdk/resolution_support.py
wev/sdk/test_exceptions.py
wev/state/__init__.py
wev/state/base_state.py
wev/state/mock_state.py
wev/state/py.typed
wev/state/state.py
wev/state/test_state.py
wev/text/__init__.py
wev/text/datetime.py
wev/text/normalize.py
wev/text/py.typed
wev/text/styled.py
wev/text/test_datetime.py
wev/text/test_normalize.py
wev/wev_echo/__init__.py
wev/wev_echo/plugin.py
wev/wev_echo/test_plugin.py
wev-1.3.5.dist-info/METADATA
wev-1.3.5.dist-info/WHEEL
wev-1.3.5.dist-info/entry_points.txt
wev-1.3.5.dist-info/top_level.txt
wev-1.3.5.dist-info/RECORD
