Metadata-Version: 2.1
Name: wev
Version: 1.3.5
Summary: Run shell commands with environment variables
Home-page: https://github.com/cariad/wev
Author: Cariad Eccleston
Author-email: cariad@cariad.me
License: MIT License
Platform: UNKNOWN
Classifier: Development Status :: 5 - Production/Stable
Classifier: Environment :: Console
Classifier: Intended Audience :: Developers
Classifier: License :: OSI Approved :: MIT License
Classifier: Natural Language :: English
Classifier: Operating System :: OS Independent
Classifier: Programming Language :: Python :: 3 :: Only
Classifier: Programming Language :: Python :: 3.8
Classifier: Programming Language :: Python :: 3.9
Classifier: Topic :: Internet
Classifier: Topic :: Security
Classifier: Topic :: Utilities
Requires-Python: >=3.8
Requires-Dist: colorama (>=0.4)
Requires-Dist: dwalk (>=1.1)
Requires-Dist: pytz (>=2020.5)
Requires-Dist: ruamel.yaml (>=0.16)
